flask_tinify/__init__.py
flask_tinify/client.py
flask_tinify/errors.py
flask_tinify/extension.py
flask_tinify/result.py
flask_tinify/result_meta.py
flask_tinify/source.py
flask_tinify/version.py
flask_tinify/data/cacert.pem
flask_tinify-1.7.dist-info/LICENSE
flask_tinify-1.7.dist-info/METADATA
flask_tinify-1.7.dist-info/WHEEL
flask_tinify-1.7.dist-info/top_level.txt
flask_tinify-1.7.dist-info/RECORD
