Metadata-Version: 2.1
Name: flask-tinify
Version: 1.7
Summary: An adaption of tinify as a flask extension
Home-page: https://github.com/minecraftschurli/flask_tinify
Author: Minecraftschurli
Author-email: minecraftschurli@gmail.com
License: MIT
Platform: UNKNOWN
Classifier: Environment :: Web Environment
Classifier: Intended Audience :: Developers
Classifier: License :: OSI Approved :: MIT License
Classifier: Operating System :: OS Independent
Classifier: Programming Language :: Python
Classifier: Programming Language :: Python :: 3
Classifier: Programming Language :: Python :: 3.6
Classifier: Topic :: Internet :: WWW/HTTP :: Dynamic Content
Classifier: Topic :: Software Development :: Libraries :: Python Modules
Requires-Dist: flask
Requires-Dist: requests
